MANIFEST.in
README.md
requirements.txt
setup.cfg
setup.py
fpakman/__init__.py
fpakman/app.py
fpakman.egg-info/PKG-INFO
fpakman.egg-info/SOURCES.txt
fpakman.egg-info/dependency_links.txt
fpakman.egg-info/entry_points.txt
fpakman.egg-info/requires.txt
fpakman.egg-info/top_level.txt
fpakman/core/__init__.py
fpakman/core/constants.py
fpakman/core/controller.py
fpakman/core/disk.py
fpakman/core/exception.py
fpakman/core/model.py
fpakman/core/resource.py
fpakman/core/system.py
fpakman/core/worker.py
fpakman/core/flatpak/__init__.py
fpakman/core/flatpak/constants.py
fpakman/core/flatpak/controller.py
fpakman/core/flatpak/flatpak.py
fpakman/core/flatpak/model.py
fpakman/core/flatpak/worker.py
fpakman/core/snap/__init__.py
fpakman/core/snap/constants.py
fpakman/core/snap/controller.py
fpakman/core/snap/model.py
fpakman/core/snap/snap.py
fpakman/core/snap/worker.py
fpakman/resources/img/about.svg
fpakman/resources/img/app_info.svg
fpakman/resources/img/app_settings.svg
fpakman/resources/img/app_update.svg
fpakman/resources/img/checked.svg
fpakman/resources/img/downgrade.svg
fpakman/resources/img/exclamation.svg
fpakman/resources/img/flathub.svg
fpakman/resources/img/history.svg
fpakman/resources/img/install.svg
fpakman/resources/img/logo.png
fpakman/resources/img/logo.svg
fpakman/resources/img/logo_update.png
fpakman/resources/img/logo_update.svg
fpakman/resources/img/red_cross.svg
fpakman/resources/img/refresh.svg
fpakman/resources/img/search.svg
fpakman/resources/img/snapcraft.png
fpakman/resources/img/uninstall.svg
fpakman/resources/img/update_green.svg
fpakman/resources/img/update_logo.svg
fpakman/resources/locale/en
fpakman/resources/locale/en.orig
fpakman/resources/locale/es
fpakman/resources/locale/es.orig
fpakman/resources/locale/pt
fpakman/resources/locale/pt.orig
fpakman/util/__init__.py
fpakman/util/cache.py
fpakman/util/memory.py
fpakman/util/util.py
fpakman/view/__init__.py
fpakman/view/qt/__init__.py
fpakman/view/qt/about.py
fpakman/view/qt/apps_table.py
fpakman/view/qt/dialog.py
fpakman/view/qt/history.py
fpakman/view/qt/info.py
fpakman/view/qt/root.py
fpakman/view/qt/systray.py
fpakman/view/qt/thread.py
fpakman/view/qt/view_model.py
