Metadata-Version: 1.2
Name: fpakman
Version: 0.5.1
Summary: Graphical user interface to manage Flatpak / Snap applications.
Home-page: https://github.com/vinifmor/fpakman
Author: Vinicius Moreira
Author-email: vinicius_fmoreira@hotmail.com
License: zlib/libpng
Platform: UNKNOWN
Classifier: Topic :: Utilities
Classifier: Programming Language :: Python
Classifier: Programming Language :: Python :: 3.5
Classifier: Programming Language :: Python :: 3.6
Classifier: Programming Language :: Python :: 3.7
Requires-Python: >=3.5
